pdbme/__init__.py
pdbme/rpdb.py
pdbme/arpdb/__init__.py
pdbme/arpdb/arpdb.py
pdbme-0.0.1.data/scripts/pdbme-cli
pdbme-0.0.1.dist-info/LICENSE.txt
pdbme-0.0.1.dist-info/METADATA
pdbme-0.0.1.dist-info/WHEEL
pdbme-0.0.1.dist-info/top_level.txt
pdbme-0.0.1.dist-info/RECORD
