Metadata-Version: 2.1
Name: pdbme
Version: 0.0.1
Summary: remote pdb which connects to developer
Home-page: http://github.com/mahomahomaho/pdbme
Author: Łukasz Mach
Author-email: maho@pagema.net
License: UNKNOWN
Platform: UNKNOWN
Classifier: Environment :: Console
Classifier: Intended Audience :: Developers
Classifier: License :: OSI Approved :: ISC License (ISCL)
Classifier: Operating System :: MacOS :: MacOS X
Classifier: Operating System :: POSIX
Classifier: Programming Language :: Python :: 3.0
Classifier: Programming Language :: Python :: 3.1
Classifier: Programming Language :: Python :: 3.5
Classifier: Programming Language :: Python :: 3.7
Classifier: Topic :: Software Development :: Debuggers
Requires: click
